odoo/addons/mgmtsystem/README.rst
odoo/addons/mgmtsystem/__init__.py
odoo/addons/mgmtsystem/__manifest__.py
odoo/addons/mgmtsystem/i18n/am.po
odoo/addons/mgmtsystem/i18n/ca.po
odoo/addons/mgmtsystem/i18n/cs.po
odoo/addons/mgmtsystem/i18n/de.po
odoo/addons/mgmtsystem/i18n/el_GR.po
odoo/addons/mgmtsystem/i18n/es.po
odoo/addons/mgmtsystem/i18n/es_CL.po
odoo/addons/mgmtsystem/i18n/es_CO.po
odoo/addons/mgmtsystem/i18n/es_CR.po
odoo/addons/mgmtsystem/i18n/es_EC.po
odoo/addons/mgmtsystem/i18n/es_ES.po
odoo/addons/mgmtsystem/i18n/es_MX.po
odoo/addons/mgmtsystem/i18n/es_VE.po
odoo/addons/mgmtsystem/i18n/et.po
odoo/addons/mgmtsystem/i18n/fi.po
odoo/addons/mgmtsystem/i18n/fr.po
odoo/addons/mgmtsystem/i18n/gl.po
odoo/addons/mgmtsystem/i18n/hr_HR.po
odoo/addons/mgmtsystem/i18n/hu.po
odoo/addons/mgmtsystem/i18n/it.po
odoo/addons/mgmtsystem/i18n/lt.po
odoo/addons/mgmtsystem/i18n/lv.po
odoo/addons/mgmtsystem/i18n/mgmtsystem.pot
odoo/addons/mgmtsystem/i18n/nb.po
odoo/addons/mgmtsystem/i18n/nl.po
odoo/addons/mgmtsystem/i18n/nl_BE.po
odoo/addons/mgmtsystem/i18n/nl_NL.po
odoo/addons/mgmtsystem/i18n/nn.po
odoo/addons/mgmtsystem/i18n/pl.po
odoo/addons/mgmtsystem/i18n/pt.po
odoo/addons/mgmtsystem/i18n/pt_BR.po
odoo/addons/mgmtsystem/i18n/pt_PT.po
odoo/addons/mgmtsystem/i18n/ro.po
odoo/addons/mgmtsystem/i18n/ru.po
odoo/addons/mgmtsystem/i18n/sl.po
odoo/addons/mgmtsystem/i18n/sv.po
odoo/addons/mgmtsystem/i18n/th.po
odoo/addons/mgmtsystem/i18n/tr.po
odoo/addons/mgmtsystem/i18n/vi.po
odoo/addons/mgmtsystem/i18n/zh_CN.po
odoo/addons/mgmtsystem/models/__init__.py
odoo/addons/mgmtsystem/models/mgmtsystem_system.py
odoo/addons/mgmtsystem/models/res_config.py
odoo/addons/mgmtsystem/security/ir.model.access.csv
odoo/addons/mgmtsystem/security/mgmtsystem_security.xml
odoo/addons/mgmtsystem/static/description/icon.png
odoo/addons/mgmtsystem/static/description/icon.svg
odoo/addons/mgmtsystem/tests/__init__.py
odoo/addons/mgmtsystem/tests/test_create_mgmtsystem.py
odoo11_addon_mgmtsystem-11.0.1.0.0.99.dev17.dist-info/METADATA
odoo11_addon_mgmtsystem-11.0.1.0.0.99.dev17.dist-info/WHEEL
odoo11_addon_mgmtsystem-11.0.1.0.0.99.dev17.dist-info/top_level.txt
odoo11_addon_mgmtsystem-11.0.1.0.0.99.dev17.dist-info/RECORD
